{
  "findings": [
    {
      "kind": "pattern",
      "lang": "node",
      "file": "C:\\Users\\Ckhadar\\Downloads\\AI_Baseline_Map\\tmp\\analyzer\\741e5598-b64c-4f9c-9af0-4302e358d057-analyzer-fixture-3.js",
      "line": 23,
      "status": "affected",
      "reason": "deprecated-api",
      "issue": "Dynamic import() can be dangerous",
      "pattern": "\\bimport\\(.*\\)",
      "quickFix": "Use static imports or proper module loading"
    },
    {
      "kind": "pattern",
      "lang": "node",
      "file": "C:\\Users\\Ckhadar\\Downloads\\AI_Baseline_Map\\tmp\\analyzer\\741e5598-b64c-4f9c-9af0-4302e358d057-analyzer-fixture-3.js",
      "line": 23,
      "status": "affected",
      "reason": "deprecated-api",
      "issue": "Dynamic import() can be dangerous",
      "pattern": "\\bimport\\(.*\\)",
      "quickFix": "Use static imports or proper module loading"
    },
    {
      "kind": "pattern",
      "lang": "node",
      "file": "C:\\Users\\Ckhadar\\Downloads\\AI_Baseline_Map\\tmp\\analyzer\\741e5598-b64c-4f9c-9af0-4302e358d057-analyzer-fixture-3.js",
      "line": 24,
      "status": "affected",
      "reason": "deprecated-api",
      "issue": "Dynamic import() can be dangerous",
      "pattern": "\\bimport\\(.*\\)",
      "quickFix": "Use static imports or proper module loading"
    },
    {
      "kind": "pattern",
      "lang": "node",
      "file": "C:\\Users\\Ckhadar\\Downloads\\AI_Baseline_Map\\tmp\\analyzer\\741e5598-b64c-4f9c-9af0-4302e358d057-analyzer-fixture-3.js",
      "line": 24,
      "status": "affected",
      "reason": "deprecated-api",
      "issue": "Dynamic import() can be dangerous",
      "pattern": "\\bimport\\(.*\\)",
      "quickFix": "Use static imports or proper module loading"
    },
    {
      "kind": "pattern",
      "lang": "node",
      "file": "C:\\Users\\Ckhadar\\Downloads\\AI_Baseline_Map\\tmp\\analyzer\\741e5598-b64c-4f9c-9af0-4302e358d057-analyzer-fixture-3.js",
      "line": 25,
      "status": "affected",
      "reason": "deprecated-api",
      "issue": "Dynamic import() can be dangerous",
      "pattern": "\\bimport\\(.*\\)",
      "quickFix": "Use static imports or proper module loading"
    },
    {
      "kind": "pattern",
      "lang": "node",
      "file": "C:\\Users\\Ckhadar\\Downloads\\AI_Baseline_Map\\tmp\\analyzer\\741e5598-b64c-4f9c-9af0-4302e358d057-analyzer-fixture-3.js",
      "line": 25,
      "status": "affected",
      "reason": "deprecated-api",
      "issue": "Dynamic import() can be dangerous",
      "pattern": "\\bimport\\(.*\\)",
      "quickFix": "Use static imports or proper module loading"
    },
    {
      "kind": "pattern",
      "lang": "node",
      "file": "C:\\Users\\Ckhadar\\Downloads\\AI_Baseline_Map\\tmp\\analyzer\\741e5598-b64c-4f9c-9af0-4302e358d057-analyzer-fixture-3.js",
      "line": 26,
      "status": "affected",
      "reason": "deprecated-api",
      "issue": "Dynamic import() can be dangerous",
      "pattern": "\\bimport\\(.*\\)",
      "quickFix": "Use static imports or proper module loading"
    },
    {
      "kind": "pattern",
      "lang": "node",
      "file": "C:\\Users\\Ckhadar\\Downloads\\AI_Baseline_Map\\tmp\\analyzer\\741e5598-b64c-4f9c-9af0-4302e358d057-analyzer-fixture-3.js",
      "line": 26,
      "status": "affected",
      "reason": "deprecated-api",
      "issue": "Dynamic import() can be dangerous",
      "pattern": "\\bimport\\(.*\\)",
      "quickFix": "Use static imports or proper module loading"
    },
    {
      "kind": "pattern",
      "lang": "node",
      "file": "C:\\Users\\Ckhadar\\Downloads\\AI_Baseline_Map\\tmp\\analyzer\\741e5598-b64c-4f9c-9af0-4302e358d057-analyzer-fixture-3.js",
      "line": 27,
      "status": "affected",
      "reason": "deprecated-api",
      "issue": "Dynamic import() can be dangerous",
      "pattern": "\\bimport\\(.*\\)",
      "quickFix": "Use static imports or proper module loading"
    },
    {
      "kind": "pattern",
      "lang": "node",
      "file": "C:\\Users\\Ckhadar\\Downloads\\AI_Baseline_Map\\tmp\\analyzer\\741e5598-b64c-4f9c-9af0-4302e358d057-analyzer-fixture-3.js",
      "line": 27,
      "status": "affected",
      "reason": "deprecated-api",
      "issue": "Dynamic import() can be dangerous",
      "pattern": "\\bimport\\(.*\\)",
      "quickFix": "Use static imports or proper module loading"
    },
    {
      "kind": "pattern",
      "lang": "node",
      "file": "C:\\Users\\Ckhadar\\Downloads\\AI_Baseline_Map\\tmp\\analyzer\\741e5598-b64c-4f9c-9af0-4302e358d057-analyzer-fixture-3.js",
      "line": 28,
      "status": "affected",
      "reason": "deprecated-api",
      "issue": "Dynamic import() can be dangerous",
      "pattern": "\\bimport\\(.*\\)",
      "quickFix": "Use static imports or proper module loading"
    },
    {
      "kind": "pattern",
      "lang": "node",
      "file": "C:\\Users\\Ckhadar\\Downloads\\AI_Baseline_Map\\tmp\\analyzer\\741e5598-b64c-4f9c-9af0-4302e358d057-analyzer-fixture-3.js",
      "line": 28,
      "status": "affected",
      "reason": "deprecated-api",
      "issue": "Dynamic import() can be dangerous",
      "pattern": "\\bimport\\(.*\\)",
      "quickFix": "Use static imports or proper module loading"
    },
    {
      "kind": "pattern",
      "lang": "node",
      "file": "C:\\Users\\Ckhadar\\Downloads\\AI_Baseline_Map\\tmp\\analyzer\\741e5598-b64c-4f9c-9af0-4302e358d057-analyzer-fixture-3.js",
      "line": 32,
      "status": "affected",
      "reason": "deprecated-api",
      "issue": "console.log() should be removed in production",
      "pattern": "\\bconsole\\.log\\(",
      "quickFix": "Use proper logging library or remove debug statements"
    },
    {
      "kind": "pattern",
      "lang": "node",
      "file": "C:\\Users\\Ckhadar\\Downloads\\AI_Baseline_Map\\tmp\\analyzer\\741e5598-b64c-4f9c-9af0-4302e358d057-analyzer-fixture-3.js",
      "line": 36,
      "status": "affected",
      "reason": "deprecated-api",
      "issue": "Function declarations are less preferred than arrow functions",
      "pattern": "function\\s+\\w+\\s*\\(",
      "quickFix": "Use arrow functions for better scope handling"
    },
    {
      "kind": "pattern",
      "lang": "node",
      "file": "C:\\Users\\Ckhadar\\Downloads\\AI_Baseline_Map\\tmp\\analyzer\\741e5598-b64c-4f9c-9af0-4302e358d057-analyzer-fixture-3.js",
      "line": 40,
      "status": "affected",
      "reason": "deprecated-api",
      "issue": "Post-increment can be confusing",
      "pattern": "\\b\\w+\\s*\\+\\+",
      "quickFix": "Use pre-increment or explicit addition"
    },
    {
      "kind": "pattern",
      "lang": "node",
      "file": "C:\\Users\\Ckhadar\\Downloads\\AI_Baseline_Map\\tmp\\analyzer\\741e5598-b64c-4f9c-9af0-4302e358d057-analyzer-fixture-3.js",
      "line": 40,
      "status": "affected",
      "reason": "deprecated-api",
      "issue": "Compound assignment can be confusing",
      "pattern": "\\b\\w+\\s*\\+=\\s*\\w+",
      "quickFix": "Use explicit addition"
    },
    {
      "kind": "pattern",
      "lang": "node",
      "file": "C:\\Users\\Ckhadar\\Downloads\\AI_Baseline_Map\\tmp\\analyzer\\741e5598-b64c-4f9c-9af0-4302e358d057-analyzer-fixture-3.js",
      "line": 49,
      "status": "affected",
      "reason": "deprecated-api",
      "issue": "Function declarations are less preferred than arrow functions",
      "pattern": "function\\s+\\w+\\s*\\(",
      "quickFix": "Use arrow functions for better scope handling"
    },
    {
      "kind": "pattern",
      "lang": "node",
      "file": "C:\\Users\\Ckhadar\\Downloads\\AI_Baseline_Map\\tmp\\analyzer\\741e5598-b64c-4f9c-9af0-4302e358d057-analyzer-fixture-3.js",
      "line": 55,
      "status": "affected",
      "reason": "deprecated-api",
      "issue": "Check for potential logical operator misuse",
      "pattern": "\\b\\w+\\s*\\|\\|\\s*\\w+",
      "quickFix": "Use explicit boolean checks"
    },
    {
      "kind": "pattern",
      "lang": "node",
      "file": "C:\\Users\\Ckhadar\\Downloads\\AI_Baseline_Map\\tmp\\analyzer\\741e5598-b64c-4f9c-9af0-4302e358d057-analyzer-fixture-3.js",
      "line": 61,
      "status": "affected",
      "reason": "deprecated-api",
      "issue": "Function declarations are less preferred than arrow functions",
      "pattern": "function\\s+\\w+\\s*\\(",
      "quickFix": "Use arrow functions for better scope handling"
    },
    {
      "kind": "pattern",
      "lang": "node",
      "file": "C:\\Users\\Ckhadar\\Downloads\\AI_Baseline_Map\\tmp\\analyzer\\741e5598-b64c-4f9c-9af0-4302e358d057-analyzer-fixture-3.js",
      "line": 64,
      "status": "affected",
      "reason": "deprecated-api",
      "issue": "Function declarations are less preferred than arrow functions",
      "pattern": "function\\s+\\w+\\s*\\(",
      "quickFix": "Use arrow functions for better scope handling"
    },
    {
      "kind": "pattern",
      "lang": "node",
      "file": "C:\\Users\\Ckhadar\\Downloads\\AI_Baseline_Map\\tmp\\analyzer\\741e5598-b64c-4f9c-9af0-4302e358d057-analyzer-fixture-3.js",
      "line": 69,
      "status": "affected",
      "reason": "deprecated-api",
      "issue": "Function declarations are less preferred than arrow functions",
      "pattern": "function\\s+\\w+\\s*\\(",
      "quickFix": "Use arrow functions for better scope handling"
    },
    {
      "kind": "pattern",
      "lang": "node",
      "file": "C:\\Users\\Ckhadar\\Downloads\\AI_Baseline_Map\\tmp\\analyzer\\741e5598-b64c-4f9c-9af0-4302e358d057-analyzer-fixture-3.js",
      "line": 78,
      "status": "affected",
      "reason": "deprecated-api",
      "issue": "Function declarations are less preferred than arrow functions",
      "pattern": "function\\s+\\w+\\s*\\(",
      "quickFix": "Use arrow functions for better scope handling"
    },
    {
      "kind": "pattern",
      "lang": "node",
      "file": "C:\\Users\\Ckhadar\\Downloads\\AI_Baseline_Map\\tmp\\analyzer\\741e5598-b64c-4f9c-9af0-4302e358d057-analyzer-fixture-3.js",
      "line": 82,
      "status": "affected",
      "reason": "deprecated-api",
      "issue": "JSON.parse() with untrusted data is dangerous",
      "pattern": "\\bJSON\\.parse\\(",
      "quickFix": "Validate and sanitize input before parsing"
    },
    {
      "kind": "pattern",
      "lang": "node",
      "file": "C:\\Users\\Ckhadar\\Downloads\\AI_Baseline_Map\\tmp\\analyzer\\741e5598-b64c-4f9c-9af0-4302e358d057-analyzer-fixture-3.js",
      "line": 82,
      "status": "affected",
      "reason": "deprecated-api",
      "issue": "JSON.parse() with untrusted data is dangerous",
      "pattern": "\\bJSON\\.parse\\(",
      "quickFix": "Validate and sanitize input before parsing"
    },
    {
      "kind": "pattern",
      "lang": "node",
      "file": "C:\\Users\\Ckhadar\\Downloads\\AI_Baseline_Map\\tmp\\analyzer\\741e5598-b64c-4f9c-9af0-4302e358d057-analyzer-fixture-3.js",
      "line": 85,
      "status": "affected",
      "reason": "deprecated-api",
      "issue": "Function declarations are less preferred than arrow functions",
      "pattern": "function\\s+\\w+\\s*\\(",
      "quickFix": "Use arrow functions for better scope handling"
    },
    {
      "kind": "pattern",
      "lang": "node",
      "file": "C:\\Users\\Ckhadar\\Downloads\\AI_Baseline_Map\\tmp\\analyzer\\741e5598-b64c-4f9c-9af0-4302e358d057-analyzer-fixture-3.js",
      "line": 97,
      "status": "affected",
      "reason": "deprecated-api",
      "issue": "Function declarations are less preferred than arrow functions",
      "pattern": "function\\s+\\w+\\s*\\(",
      "quickFix": "Use arrow functions for better scope handling"
    },
    {
      "kind": "pattern",
      "lang": "node",
      "file": "C:\\Users\\Ckhadar\\Downloads\\AI_Baseline_Map\\tmp\\analyzer\\741e5598-b64c-4f9c-9af0-4302e358d057-analyzer-fixture-3.js",
      "line": 99,
      "status": "affected",
      "reason": "deprecated-api",
      "issue": "new Buffer() is deprecated, use Buffer.from() or Buffer.alloc()",
      "pattern": "new Buffer\\(",
      "quickFix": "Use Buffer.from() for strings or Buffer.alloc() for size"
    },
    {
      "kind": "pattern",
      "lang": "node",
      "file": "C:\\Users\\Ckhadar\\Downloads\\AI_Baseline_Map\\tmp\\analyzer\\741e5598-b64c-4f9c-9af0-4302e358d057-analyzer-fixture-3.js",
      "line": 103,
      "status": "affected",
      "reason": "deprecated-api",
      "issue": "Function declarations are less preferred than arrow functions",
      "pattern": "function\\s+\\w+\\s*\\(",
      "quickFix": "Use arrow functions for better scope handling"
    },
    {
      "kind": "pattern",
      "lang": "node",
      "file": "C:\\Users\\Ckhadar\\Downloads\\AI_Baseline_Map\\tmp\\analyzer\\741e5598-b64c-4f9c-9af0-4302e358d057-analyzer-fixture-3.js",
      "line": 111,
      "status": "affected",
      "reason": "deprecated-api",
      "issue": "Function declarations are less preferred than arrow functions",
      "pattern": "function\\s+\\w+\\s*\\(",
      "quickFix": "Use arrow functions for better scope handling"
    },
    {
      "kind": "pattern",
      "lang": "node",
      "file": "C:\\Users\\Ckhadar\\Downloads\\AI_Baseline_Map\\tmp\\analyzer\\741e5598-b64c-4f9c-9af0-4302e358d057-analyzer-fixture-3.js",
      "line": 120,
      "status": "affected",
      "reason": "deprecated-api",
      "issue": "Function declarations are less preferred than arrow functions",
      "pattern": "function\\s+\\w+\\s*\\(",
      "quickFix": "Use arrow functions for better scope handling"
    },
    {
      "kind": "pattern",
      "lang": "node",
      "file": "C:\\Users\\Ckhadar\\Downloads\\AI_Baseline_Map\\tmp\\analyzer\\741e5598-b64c-4f9c-9af0-4302e358d057-analyzer-fixture-3.js",
      "line": 128,
      "status": "affected",
      "reason": "deprecated-api",
      "issue": "Function declarations are less preferred than arrow functions",
      "pattern": "function\\s+\\w+\\s*\\(",
      "quickFix": "Use arrow functions for better scope handling"
    },
    {
      "kind": "pattern",
      "lang": "node",
      "file": "C:\\Users\\Ckhadar\\Downloads\\AI_Baseline_Map\\tmp\\analyzer\\741e5598-b64c-4f9c-9af0-4302e358d057-analyzer-fixture-3.js",
      "line": 135,
      "status": "affected",
      "reason": "deprecated-api",
      "issue": "Function declarations are less preferred than arrow functions",
      "pattern": "function\\s+\\w+\\s*\\(",
      "quickFix": "Use arrow functions for better scope handling"
    },
    {
      "kind": "pattern",
      "lang": "node",
      "file": "C:\\Users\\Ckhadar\\Downloads\\AI_Baseline_Map\\tmp\\analyzer\\741e5598-b64c-4f9c-9af0-4302e358d057-analyzer-fixture-3.js",
      "line": 142,
      "status": "affected",
      "reason": "deprecated-api",
      "issue": "Function declarations are less preferred than arrow functions",
      "pattern": "function\\s+\\w+\\s*\\(",
      "quickFix": "Use arrow functions for better scope handling"
    },
    {
      "kind": "pattern",
      "lang": "node",
      "file": "C:\\Users\\Ckhadar\\Downloads\\AI_Baseline_Map\\tmp\\analyzer\\741e5598-b64c-4f9c-9af0-4302e358d057-analyzer-fixture-3.js",
      "line": 144,
      "status": "affected",
      "reason": "deprecated-api",
      "issue": "Check for potential logical operator misuse",
      "pattern": "\\b\\w+\\s*\\|\\|\\s*\\w+",
      "quickFix": "Use explicit boolean checks"
    },
    {
      "kind": "pattern",
      "lang": "node",
      "file": "C:\\Users\\Ckhadar\\Downloads\\AI_Baseline_Map\\tmp\\analyzer\\741e5598-b64c-4f9c-9af0-4302e358d057-analyzer-fixture-3.js",
      "line": 144,
      "status": "affected",
      "reason": "deprecated-api",
      "issue": "setTimeout with string is dangerous",
      "pattern": "\\bsetTimeout\\(",
      "quickFix": "Use function references instead of strings"
    },
    {
      "kind": "pattern",
      "lang": "node",
      "file": "C:\\Users\\Ckhadar\\Downloads\\AI_Baseline_Map\\tmp\\analyzer\\741e5598-b64c-4f9c-9af0-4302e358d057-analyzer-fixture-3.js",
      "line": 144,
      "status": "affected",
      "reason": "deprecated-api",
      "issue": "setTimeout with string is dangerous",
      "pattern": "\\bsetTimeout\\(",
      "quickFix": "Use function references instead of strings"
    },
    {
      "kind": "pattern",
      "lang": "node",
      "file": "C:\\Users\\Ckhadar\\Downloads\\AI_Baseline_Map\\tmp\\analyzer\\741e5598-b64c-4f9c-9af0-4302e358d057-analyzer-fixture-3.js",
      "line": 147,
      "status": "affected",
      "reason": "deprecated-api",
      "issue": "Function declarations are less preferred than arrow functions",
      "pattern": "function\\s+\\w+\\s*\\(",
      "quickFix": "Use arrow functions for better scope handling"
    },
    {
      "kind": "pattern",
      "lang": "node",
      "file": "C:\\Users\\Ckhadar\\Downloads\\AI_Baseline_Map\\tmp\\analyzer\\741e5598-b64c-4f9c-9af0-4302e358d057-analyzer-fixture-3.js",
      "line": 152,
      "status": "affected",
      "reason": "deprecated-api",
      "issue": "Function declarations are less preferred than arrow functions",
      "pattern": "function\\s+\\w+\\s*\\(",
      "quickFix": "Use arrow functions for better scope handling"
    },
    {
      "kind": "pattern",
      "lang": "node",
      "file": "C:\\Users\\Ckhadar\\Downloads\\AI_Baseline_Map\\tmp\\analyzer\\741e5598-b64c-4f9c-9af0-4302e358d057-analyzer-fixture-3.js",
      "line": 157,
      "status": "affected",
      "reason": "deprecated-api",
      "issue": "Function declarations are less preferred than arrow functions",
      "pattern": "function\\s+\\w+\\s*\\(",
      "quickFix": "Use arrow functions for better scope handling"
    },
    {
      "kind": "pattern",
      "lang": "node",
      "file": "C:\\Users\\Ckhadar\\Downloads\\AI_Baseline_Map\\tmp\\analyzer\\741e5598-b64c-4f9c-9af0-4302e358d057-analyzer-fixture-3.js",
      "line": 164,
      "status": "affected",
      "reason": "deprecated-api",
      "issue": "Function declarations are less preferred than arrow functions",
      "pattern": "function\\s+\\w+\\s*\\(",
      "quickFix": "Use arrow functions for better scope handling"
    },
    {
      "kind": "pattern",
      "lang": "node",
      "file": "C:\\Users\\Ckhadar\\Downloads\\AI_Baseline_Map\\tmp\\analyzer\\741e5598-b64c-4f9c-9af0-4302e358d057-analyzer-fixture-3.js",
      "line": 165,
      "status": "affected",
      "reason": "deprecated-api",
      "issue": "typeof undefined check is verbose",
      "pattern": "\\btypeof\\s+\\w+\\s*===\\s*['\"]undefined['\"]",
      "quickFix": "Use === undefined or optional chaining"
    },
    {
      "kind": "pattern",
      "lang": "node",
      "file": "C:\\Users\\Ckhadar\\Downloads\\AI_Baseline_Map\\tmp\\analyzer\\741e5598-b64c-4f9c-9af0-4302e358d057-analyzer-fixture-3.js",
      "line": 177,
      "status": "affected",
      "reason": "deprecated-api",
      "issue": "Function declarations are less preferred than arrow functions",
      "pattern": "function\\s+\\w+\\s*\\(",
      "quickFix": "Use arrow functions for better scope handling"
    },
    {
      "kind": "pattern",
      "lang": "node",
      "file": "C:\\Users\\Ckhadar\\Downloads\\AI_Baseline_Map\\tmp\\analyzer\\741e5598-b64c-4f9c-9af0-4302e358d057-analyzer-fixture-3.js",
      "line": 178,
      "status": "affected",
      "reason": "deprecated-api",
      "issue": "typeof undefined check is verbose",
      "pattern": "\\btypeof\\s+\\w+\\s*===\\s*['\"]undefined['\"]",
      "quickFix": "Use === undefined or optional chaining"
    },
    {
      "kind": "pattern",
      "lang": "node",
      "file": "C:\\Users\\Ckhadar\\Downloads\\AI_Baseline_Map\\tmp\\analyzer\\741e5598-b64c-4f9c-9af0-4302e358d057-analyzer-fixture-3.js",
      "line": 193,
      "status": "affected",
      "reason": "deprecated-api",
      "issue": "Direct this assignment is discouraged",
      "pattern": "\\bthis\\.\\w+\\s*=",
      "quickFix": "Use class properties or bind methods properly"
    },
    {
      "kind": "pattern",
      "lang": "node",
      "file": "C:\\Users\\Ckhadar\\Downloads\\AI_Baseline_Map\\tmp\\analyzer\\741e5598-b64c-4f9c-9af0-4302e358d057-analyzer-fixture-3.js",
      "line": 194,
      "status": "affected",
      "reason": "deprecated-api",
      "issue": "Direct this assignment is discouraged",
      "pattern": "\\bthis\\.\\w+\\s*=",
      "quickFix": "Use class properties or bind methods properly"
    },
    {
      "kind": "pattern",
      "lang": "node",
      "file": "C:\\Users\\Ckhadar\\Downloads\\AI_Baseline_Map\\tmp\\analyzer\\741e5598-b64c-4f9c-9af0-4302e358d057-analyzer-fixture-3.js",
      "line": 197,
      "status": "affected",
      "reason": "deprecated-api",
      "issue": "Post-increment can be confusing",
      "pattern": "\\b\\w+\\s*\\+\\+",
      "quickFix": "Use pre-increment or explicit addition"
    },
    {
      "kind": "pattern",
      "lang": "node",
      "file": "C:\\Users\\Ckhadar\\Downloads\\AI_Baseline_Map\\tmp\\analyzer\\741e5598-b64c-4f9c-9af0-4302e358d057-analyzer-fixture-3.js",
      "line": 201,
      "status": "affected",
      "reason": "deprecated-api",
      "issue": "console.log() should be removed in production",
      "pattern": "\\bconsole\\.log\\(",
      "quickFix": "Use proper logging library or remove debug statements"
    },
    {
      "kind": "pattern",
      "lang": "node",
      "file": "C:\\Users\\Ckhadar\\Downloads\\AI_Baseline_Map\\tmp\\analyzer\\741e5598-b64c-4f9c-9af0-4302e358d057-analyzer-fixture-3.js",
      "line": 205,
      "status": "affected",
      "reason": "deprecated-api",
      "issue": "Function declarations are less preferred than arrow functions",
      "pattern": "function\\s+\\w+\\s*\\(",
      "quickFix": "Use arrow functions for better scope handling"
    },
    {
      "kind": "pattern",
      "lang": "node",
      "file": "C:\\Users\\Ckhadar\\Downloads\\AI_Baseline_Map\\tmp\\analyzer\\741e5598-b64c-4f9c-9af0-4302e358d057-analyzer-fixture-3.js",
      "line": 210,
      "status": "affected",
      "reason": "deprecated-api",
      "issue": "Function declarations are less preferred than arrow functions",
      "pattern": "function\\s+\\w+\\s*\\(",
      "quickFix": "Use arrow functions for better scope handling"
    },
    {
      "kind": "pattern",
      "lang": "node",
      "file": "C:\\Users\\Ckhadar\\Downloads\\AI_Baseline_Map\\tmp\\analyzer\\741e5598-b64c-4f9c-9af0-4302e358d057-analyzer-fixture-3.js",
      "line": 212,
      "status": "affected",
      "reason": "deprecated-api",
      "issue": "== can cause type coercion issues",
      "pattern": "\\b\\w+\\s*==\\s*\\w+",
      "quickFix": "Use === for strict equality"
    },
    {
      "kind": "pattern",
      "lang": "node",
      "file": "C:\\Users\\Ckhadar\\Downloads\\AI_Baseline_Map\\tmp\\analyzer\\741e5598-b64c-4f9c-9af0-4302e358d057-analyzer-fixture-3.js",
      "line": 246,
      "status": "affected",
      "reason": "deprecated-api",
      "issue": "Dynamic import() can be dangerous",
      "pattern": "\\bimport\\(.*\\)",
      "quickFix": "Use static imports or proper module loading"
    },
    {
      "kind": "pattern",
      "lang": "node",
      "file": "C:\\Users\\Ckhadar\\Downloads\\AI_Baseline_Map\\tmp\\analyzer\\741e5598-b64c-4f9c-9af0-4302e358d057-analyzer-fixture-3.js",
      "line": 246,
      "status": "affected",
      "reason": "deprecated-api",
      "issue": "Dynamic import() can be dangerous",
      "pattern": "\\bimport\\(.*\\)",
      "quickFix": "Use static imports or proper module loading"
    },
    {
      "kind": "pattern",
      "lang": "node",
      "file": "C:\\Users\\Ckhadar\\Downloads\\AI_Baseline_Map\\tmp\\analyzer\\741e5598-b64c-4f9c-9af0-4302e358d057-analyzer-fixture-3.js",
      "line": 23,
      "status": "affected",
      "reason": "deprecated-api",
      "issue": "Dynamic import() can be dangerous",
      "pattern": "import\\s*\\(\\s*['\"]",
      "quickFix": "Use static imports or proper module loading"
    },
    {
      "kind": "pattern",
      "lang": "node",
      "file": "C:\\Users\\Ckhadar\\Downloads\\AI_Baseline_Map\\tmp\\analyzer\\741e5598-b64c-4f9c-9af0-4302e358d057-analyzer-fixture-3.js",
      "line": 24,
      "status": "affected",
      "reason": "deprecated-api",
      "issue": "Dynamic import() can be dangerous",
      "pattern": "import\\s*\\(\\s*['\"]",
      "quickFix": "Use static imports or proper module loading"
    },
    {
      "kind": "pattern",
      "lang": "node",
      "file": "C:\\Users\\Ckhadar\\Downloads\\AI_Baseline_Map\\tmp\\analyzer\\741e5598-b64c-4f9c-9af0-4302e358d057-analyzer-fixture-3.js",
      "line": 25,
      "status": "affected",
      "reason": "deprecated-api",
      "issue": "Dynamic import() can be dangerous",
      "pattern": "import\\s*\\(\\s*['\"]",
      "quickFix": "Use static imports or proper module loading"
    },
    {
      "kind": "pattern",
      "lang": "node",
      "file": "C:\\Users\\Ckhadar\\Downloads\\AI_Baseline_Map\\tmp\\analyzer\\741e5598-b64c-4f9c-9af0-4302e358d057-analyzer-fixture-3.js",
      "line": 26,
      "status": "affected",
      "reason": "deprecated-api",
      "issue": "Dynamic import() can be dangerous",
      "pattern": "import\\s*\\(\\s*['\"]",
      "quickFix": "Use static imports or proper module loading"
    },
    {
      "kind": "pattern",
      "lang": "node",
      "file": "C:\\Users\\Ckhadar\\Downloads\\AI_Baseline_Map\\tmp\\analyzer\\741e5598-b64c-4f9c-9af0-4302e358d057-analyzer-fixture-3.js",
      "line": 27,
      "status": "affected",
      "reason": "deprecated-api",
      "issue": "Dynamic import() can be dangerous",
      "pattern": "import\\s*\\(\\s*['\"]",
      "quickFix": "Use static imports or proper module loading"
    },
    {
      "kind": "pattern",
      "lang": "node",
      "file": "C:\\Users\\Ckhadar\\Downloads\\AI_Baseline_Map\\tmp\\analyzer\\741e5598-b64c-4f9c-9af0-4302e358d057-analyzer-fixture-3.js",
      "line": 28,
      "status": "affected",
      "reason": "deprecated-api",
      "issue": "Dynamic import() can be dangerous",
      "pattern": "import\\s*\\(\\s*['\"]",
      "quickFix": "Use static imports or proper module loading"
    },
    {
      "kind": "pattern",
      "lang": "node",
      "file": "C:\\Users\\Ckhadar\\Downloads\\AI_Baseline_Map\\tmp\\analyzer\\741e5598-b64c-4f9c-9af0-4302e358d057-analyzer-fixture-3.js",
      "line": 32,
      "status": "affected",
      "reason": "deprecated-api",
      "issue": "console methods should be removed in production",
      "pattern": "console\\.(log|warn|error|info|debug|trace|dir|table|time|timeEnd|count|countReset|group|groupEnd|groupCollapsed|assert|clear|profile|profileEnd|timeStamp|markTimeline|timeline|timelineEnd|memory|exception)\\s*\\(",
      "quickFix": "Use proper logging library or remove debug statements"
    },
    {
      "kind": "pattern",
      "lang": "node",
      "file": "C:\\Users\\Ckhadar\\Downloads\\AI_Baseline_Map\\tmp\\analyzer\\741e5598-b64c-4f9c-9af0-4302e358d057-analyzer-fixture-3.js",
      "line": 36,
      "status": "affected",
      "reason": "deprecated-api",
      "issue": "Function declarations are less preferred than arrow functions",
      "pattern": "function\\s+\\w+\\s*\\(",
      "quickFix": "Use arrow functions for better scope handling"
    },
    {
      "kind": "pattern",
      "lang": "node",
      "file": "C:\\Users\\Ckhadar\\Downloads\\AI_Baseline_Map\\tmp\\analyzer\\741e5598-b64c-4f9c-9af0-4302e358d057-analyzer-fixture-3.js",
      "line": 49,
      "status": "affected",
      "reason": "deprecated-api",
      "issue": "Function declarations are less preferred than arrow functions",
      "pattern": "function\\s+\\w+\\s*\\(",
      "quickFix": "Use arrow functions for better scope handling"
    },
    {
      "kind": "pattern",
      "lang": "node",
      "file": "C:\\Users\\Ckhadar\\Downloads\\AI_Baseline_Map\\tmp\\analyzer\\741e5598-b64c-4f9c-9af0-4302e358d057-analyzer-fixture-3.js",
      "line": 61,
      "status": "affected",
      "reason": "deprecated-api",
      "issue": "Function declarations are less preferred than arrow functions",
      "pattern": "function\\s+\\w+\\s*\\(",
      "quickFix": "Use arrow functions for better scope handling"
    },
    {
      "kind": "pattern",
      "lang": "node",
      "file": "C:\\Users\\Ckhadar\\Downloads\\AI_Baseline_Map\\tmp\\analyzer\\741e5598-b64c-4f9c-9af0-4302e358d057-analyzer-fixture-3.js",
      "line": 64,
      "status": "affected",
      "reason": "deprecated-api",
      "issue": "Function declarations are less preferred than arrow functions",
      "pattern": "function\\s+\\w+\\s*\\(",
      "quickFix": "Use arrow functions for better scope handling"
    },
    {
      "kind": "pattern",
      "lang": "node",
      "file": "C:\\Users\\Ckhadar\\Downloads\\AI_Baseline_Map\\tmp\\analyzer\\741e5598-b64c-4f9c-9af0-4302e358d057-analyzer-fixture-3.js",
      "line": 69,
      "status": "affected",
      "reason": "deprecated-api",
      "issue": "Function declarations are less preferred than arrow functions",
      "pattern": "function\\s+\\w+\\s*\\(",
      "quickFix": "Use arrow functions for better scope handling"
    },
    {
      "kind": "pattern",
      "lang": "node",
      "file": "C:\\Users\\Ckhadar\\Downloads\\AI_Baseline_Map\\tmp\\analyzer\\741e5598-b64c-4f9c-9af0-4302e358d057-analyzer-fixture-3.js",
      "line": 78,
      "status": "affected",
      "reason": "deprecated-api",
      "issue": "Function declarations are less preferred than arrow functions",
      "pattern": "function\\s+\\w+\\s*\\(",
      "quickFix": "Use arrow functions for better scope handling"
    },
    {
      "kind": "pattern",
      "lang": "node",
      "file": "C:\\Users\\Ckhadar\\Downloads\\AI_Baseline_Map\\tmp\\analyzer\\741e5598-b64c-4f9c-9af0-4302e358d057-analyzer-fixture-3.js",
      "line": 85,
      "status": "affected",
      "reason": "deprecated-api",
      "issue": "Function declarations are less preferred than arrow functions",
      "pattern": "function\\s+\\w+\\s*\\(",
      "quickFix": "Use arrow functions for better scope handling"
    },
    {
      "kind": "pattern",
      "lang": "node",
      "file": "C:\\Users\\Ckhadar\\Downloads\\AI_Baseline_Map\\tmp\\analyzer\\741e5598-b64c-4f9c-9af0-4302e358d057-analyzer-fixture-3.js",
      "line": 97,
      "status": "affected",
      "reason": "deprecated-api",
      "issue": "Function declarations are less preferred than arrow functions",
      "pattern": "function\\s+\\w+\\s*\\(",
      "quickFix": "Use arrow functions for better scope handling"
    },
    {
      "kind": "pattern",
      "lang": "node",
      "file": "C:\\Users\\Ckhadar\\Downloads\\AI_Baseline_Map\\tmp\\analyzer\\741e5598-b64c-4f9c-9af0-4302e358d057-analyzer-fixture-3.js",
      "line": 103,
      "status": "affected",
      "reason": "deprecated-api",
      "issue": "Function declarations are less preferred than arrow functions",
      "pattern": "function\\s+\\w+\\s*\\(",
      "quickFix": "Use arrow functions for better scope handling"
    },
    {
      "kind": "pattern",
      "lang": "node",
      "file": "C:\\Users\\Ckhadar\\Downloads\\AI_Baseline_Map\\tmp\\analyzer\\741e5598-b64c-4f9c-9af0-4302e358d057-analyzer-fixture-3.js",
      "line": 106,
      "status": "affected",
      "reason": "deprecated-api",
      "issue": "== can cause type coercion issues",
      "pattern": "==\\s*\\w+|\\w+\\s*==",
      "quickFix": "Use === for strict equality"
    },
    {
      "kind": "pattern",
      "lang": "node",
      "file": "C:\\Users\\Ckhadar\\Downloads\\AI_Baseline_Map\\tmp\\analyzer\\741e5598-b64c-4f9c-9af0-4302e358d057-analyzer-fixture-3.js",
      "line": 111,
      "status": "affected",
      "reason": "deprecated-api",
      "issue": "Function declarations are less preferred than arrow functions",
      "pattern": "function\\s+\\w+\\s*\\(",
      "quickFix": "Use arrow functions for better scope handling"
    },
    {
      "kind": "pattern",
      "lang": "node",
      "file": "C:\\Users\\Ckhadar\\Downloads\\AI_Baseline_Map\\tmp\\analyzer\\741e5598-b64c-4f9c-9af0-4302e358d057-analyzer-fixture-3.js",
      "line": 120,
      "status": "affected",
      "reason": "deprecated-api",
      "issue": "Function declarations are less preferred than arrow functions",
      "pattern": "function\\s+\\w+\\s*\\(",
      "quickFix": "Use arrow functions for better scope handling"
    },
    {
      "kind": "pattern",
      "lang": "node",
      "file": "C:\\Users\\Ckhadar\\Downloads\\AI_Baseline_Map\\tmp\\analyzer\\741e5598-b64c-4f9c-9af0-4302e358d057-analyzer-fixture-3.js",
      "line": 128,
      "status": "affected",
      "reason": "deprecated-api",
      "issue": "Function declarations are less preferred than arrow functions",
      "pattern": "function\\s+\\w+\\s*\\(",
      "quickFix": "Use arrow functions for better scope handling"
    },
    {
      "kind": "pattern",
      "lang": "node",
      "file": "C:\\Users\\Ckhadar\\Downloads\\AI_Baseline_Map\\tmp\\analyzer\\741e5598-b64c-4f9c-9af0-4302e358d057-analyzer-fixture-3.js",
      "line": 135,
      "status": "affected",
      "reason": "deprecated-api",
      "issue": "Function declarations are less preferred than arrow functions",
      "pattern": "function\\s+\\w+\\s*\\(",
      "quickFix": "Use arrow functions for better scope handling"
    },
    {
      "kind": "pattern",
      "lang": "node",
      "file": "C:\\Users\\Ckhadar\\Downloads\\AI_Baseline_Map\\tmp\\analyzer\\741e5598-b64c-4f9c-9af0-4302e358d057-analyzer-fixture-3.js",
      "line": 138,
      "status": "affected",
      "reason": "deprecated-api",
      "issue": "== can cause type coercion issues",
      "pattern": "==\\s*\\w+|\\w+\\s*==",
      "quickFix": "Use === for strict equality"
    },
    {
      "kind": "pattern",
      "lang": "node",
      "file": "C:\\Users\\Ckhadar\\Downloads\\AI_Baseline_Map\\tmp\\analyzer\\741e5598-b64c-4f9c-9af0-4302e358d057-analyzer-fixture-3.js",
      "line": 142,
      "status": "affected",
      "reason": "deprecated-api",
      "issue": "Function declarations are less preferred than arrow functions",
      "pattern": "function\\s+\\w+\\s*\\(",
      "quickFix": "Use arrow functions for better scope handling"
    },
    {
      "kind": "pattern",
      "lang": "node",
      "file": "C:\\Users\\Ckhadar\\Downloads\\AI_Baseline_Map\\tmp\\analyzer\\741e5598-b64c-4f9c-9af0-4302e358d057-analyzer-fixture-3.js",
      "line": 144,
      "status": "affected",
      "reason": "deprecated-api",
      "issue": "setTimeout with string is dangerous",
      "pattern": "setTimeout\\s*\\(\\s*['\"]",
      "quickFix": "Use function references instead of strings"
    },
    {
      "kind": "pattern",
      "lang": "node",
      "file": "C:\\Users\\Ckhadar\\Downloads\\AI_Baseline_Map\\tmp\\analyzer\\741e5598-b64c-4f9c-9af0-4302e358d057-analyzer-fixture-3.js",
      "line": 147,
      "status": "affected",
      "reason": "deprecated-api",
      "issue": "Function declarations are less preferred than arrow functions",
      "pattern": "function\\s+\\w+\\s*\\(",
      "quickFix": "Use arrow functions for better scope handling"
    },
    {
      "kind": "pattern",
      "lang": "node",
      "file": "C:\\Users\\Ckhadar\\Downloads\\AI_Baseline_Map\\tmp\\analyzer\\741e5598-b64c-4f9c-9af0-4302e358d057-analyzer-fixture-3.js",
      "line": 152,
      "status": "affected",
      "reason": "deprecated-api",
      "issue": "Function declarations are less preferred than arrow functions",
      "pattern": "function\\s+\\w+\\s*\\(",
      "quickFix": "Use arrow functions for better scope handling"
    },
    {
      "kind": "pattern",
      "lang": "node",
      "file": "C:\\Users\\Ckhadar\\Downloads\\AI_Baseline_Map\\tmp\\analyzer\\741e5598-b64c-4f9c-9af0-4302e358d057-analyzer-fixture-3.js",
      "line": 157,
      "status": "affected",
      "reason": "deprecated-api",
      "issue": "Function declarations are less preferred than arrow functions",
      "pattern": "function\\s+\\w+\\s*\\(",
      "quickFix": "Use arrow functions for better scope handling"
    },
    {
      "kind": "pattern",
      "lang": "node",
      "file": "C:\\Users\\Ckhadar\\Downloads\\AI_Baseline_Map\\tmp\\analyzer\\741e5598-b64c-4f9c-9af0-4302e358d057-analyzer-fixture-3.js",
      "line": 159,
      "status": "affected",
      "reason": "deprecated-api",
      "issue": "!= can cause type coercion issues",
      "pattern": "!=\\s*\\w+|\\w+\\s*!=",
      "quickFix": "Use !== for strict inequality"
    },
    {
      "kind": "pattern",
      "lang": "node",
      "file": "C:\\Users\\Ckhadar\\Downloads\\AI_Baseline_Map\\tmp\\analyzer\\741e5598-b64c-4f9c-9af0-4302e358d057-analyzer-fixture-3.js",
      "line": 164,
      "status": "affected",
      "reason": "deprecated-api",
      "issue": "Function declarations are less preferred than arrow functions",
      "pattern": "function\\s+\\w+\\s*\\(",
      "quickFix": "Use arrow functions for better scope handling"
    },
    {
      "kind": "pattern",
      "lang": "node",
      "file": "C:\\Users\\Ckhadar\\Downloads\\AI_Baseline_Map\\tmp\\analyzer\\741e5598-b64c-4f9c-9af0-4302e358d057-analyzer-fixture-3.js",
      "line": 165,
      "status": "affected",
      "reason": "deprecated-api",
      "issue": "== can cause type coercion issues",
      "pattern": "==\\s*\\w+|\\w+\\s*==",
      "quickFix": "Use === for strict equality"
    },
    {
      "kind": "pattern",
      "lang": "node",
      "file": "C:\\Users\\Ckhadar\\Downloads\\AI_Baseline_Map\\tmp\\analyzer\\741e5598-b64c-4f9c-9af0-4302e358d057-analyzer-fixture-3.js",
      "line": 165,
      "status": "affected",
      "reason": "deprecated-api",
      "issue": "typeof undefined check is verbose",
      "pattern": "typeof\\s+\\w+\\s*===\\s*['\"]undefined['\"]",
      "quickFix": "Use === undefined or optional chaining"
    },
    {
      "kind": "pattern",
      "lang": "node",
      "file": "C:\\Users\\Ckhadar\\Downloads\\AI_Baseline_Map\\tmp\\analyzer\\741e5598-b64c-4f9c-9af0-4302e358d057-analyzer-fixture-3.js",
      "line": 177,
      "status": "affected",
      "reason": "deprecated-api",
      "issue": "Function declarations are less preferred than arrow functions",
      "pattern": "function\\s+\\w+\\s*\\(",
      "quickFix": "Use arrow functions for better scope handling"
    },
    {
      "kind": "pattern",
      "lang": "node",
      "file": "C:\\Users\\Ckhadar\\Downloads\\AI_Baseline_Map\\tmp\\analyzer\\741e5598-b64c-4f9c-9af0-4302e358d057-analyzer-fixture-3.js",
      "line": 178,
      "status": "affected",
      "reason": "deprecated-api",
      "issue": "== can cause type coercion issues",
      "pattern": "==\\s*\\w+|\\w+\\s*==",
      "quickFix": "Use === for strict equality"
    },
    {
      "kind": "pattern",
      "lang": "node",
      "file": "C:\\Users\\Ckhadar\\Downloads\\AI_Baseline_Map\\tmp\\analyzer\\741e5598-b64c-4f9c-9af0-4302e358d057-analyzer-fixture-3.js",
      "line": 178,
      "status": "affected",
      "reason": "deprecated-api",
      "issue": "typeof undefined check is verbose",
      "pattern": "typeof\\s+\\w+\\s*===\\s*['\"]undefined['\"]",
      "quickFix": "Use === undefined or optional chaining"
    },
    {
      "kind": "pattern",
      "lang": "node",
      "file": "C:\\Users\\Ckhadar\\Downloads\\AI_Baseline_Map\\tmp\\analyzer\\741e5598-b64c-4f9c-9af0-4302e358d057-analyzer-fixture-3.js",
      "line": 193,
      "status": "affected",
      "reason": "deprecated-api",
      "issue": "Direct this assignment is discouraged",
      "pattern": "this\\.\\w+\\s*=",
      "quickFix": "Use class properties or bind methods properly"
    },
    {
      "kind": "pattern",
      "lang": "node",
      "file": "C:\\Users\\Ckhadar\\Downloads\\AI_Baseline_Map\\tmp\\analyzer\\741e5598-b64c-4f9c-9af0-4302e358d057-analyzer-fixture-3.js",
      "line": 194,
      "status": "affected",
      "reason": "deprecated-api",
      "issue": "Direct this assignment is discouraged",
      "pattern": "this\\.\\w+\\s*=",
      "quickFix": "Use class properties or bind methods properly"
    },
    {
      "kind": "pattern",
      "lang": "node",
      "file": "C:\\Users\\Ckhadar\\Downloads\\AI_Baseline_Map\\tmp\\analyzer\\741e5598-b64c-4f9c-9af0-4302e358d057-analyzer-fixture-3.js",
      "line": 201,
      "status": "affected",
      "reason": "deprecated-api",
      "issue": "console methods should be removed in production",
      "pattern": "console\\.(log|warn|error|info|debug|trace|dir|table|time|timeEnd|count|countReset|group|groupEnd|groupCollapsed|assert|clear|profile|profileEnd|timeStamp|markTimeline|timeline|timelineEnd|memory|exception)\\s*\\(",
      "quickFix": "Use proper logging library or remove debug statements"
    },
    {
      "kind": "pattern",
      "lang": "node",
      "file": "C:\\Users\\Ckhadar\\Downloads\\AI_Baseline_Map\\tmp\\analyzer\\741e5598-b64c-4f9c-9af0-4302e358d057-analyzer-fixture-3.js",
      "line": 205,
      "status": "affected",
      "reason": "deprecated-api",
      "issue": "Function declarations are less preferred than arrow functions",
      "pattern": "function\\s+\\w+\\s*\\(",
      "quickFix": "Use arrow functions for better scope handling"
    },
    {
      "kind": "pattern",
      "lang": "node",
      "file": "C:\\Users\\Ckhadar\\Downloads\\AI_Baseline_Map\\tmp\\analyzer\\741e5598-b64c-4f9c-9af0-4302e358d057-analyzer-fixture-3.js",
      "line": 207,
      "status": "affected",
      "reason": "deprecated-api",
      "issue": "== can cause type coercion issues",
      "pattern": "==\\s*\\w+|\\w+\\s*==",
      "quickFix": "Use === for strict equality"
    },
    {
      "kind": "pattern",
      "lang": "node",
      "file": "C:\\Users\\Ckhadar\\Downloads\\AI_Baseline_Map\\tmp\\analyzer\\741e5598-b64c-4f9c-9af0-4302e358d057-analyzer-fixture-3.js",
      "line": 210,
      "status": "affected",
      "reason": "deprecated-api",
      "issue": "Function declarations are less preferred than arrow functions",
      "pattern": "function\\s+\\w+\\s*\\(",
      "quickFix": "Use arrow functions for better scope handling"
    },
    {
      "kind": "pattern",
      "lang": "node",
      "file": "C:\\Users\\Ckhadar\\Downloads\\AI_Baseline_Map\\tmp\\analyzer\\741e5598-b64c-4f9c-9af0-4302e358d057-analyzer-fixture-3.js",
      "line": 212,
      "status": "affected",
      "reason": "deprecated-api",
      "issue": "== can cause type coercion issues",
      "pattern": "==\\s*\\w+|\\w+\\s*==",
      "quickFix": "Use === for strict equality"
    },
    {
      "kind": "pattern",
      "lang": "node",
      "file": "C:\\Users\\Ckhadar\\Downloads\\AI_Baseline_Map\\tmp\\analyzer\\741e5598-b64c-4f9c-9af0-4302e358d057-analyzer-fixture-3.js",
      "line": 212,
      "status": "affected",
      "reason": "deprecated-api",
      "issue": "== can cause type coercion issues",
      "pattern": "==\\s*\\w+|\\w+\\s*==",
      "quickFix": "Use === for strict equality"
    },
    {
      "kind": "pattern",
      "lang": "node",
      "file": "C:\\Users\\Ckhadar\\Downloads\\AI_Baseline_Map\\tmp\\analyzer\\741e5598-b64c-4f9c-9af0-4302e358d057-analyzer-fixture-3.js",
      "line": 245,
      "status": "affected",
      "reason": "deprecated-api",
      "issue": "!= can cause type coercion issues",
      "pattern": "!=\\s*\\w+|\\w+\\s*!=",
      "quickFix": "Use !== for strict inequality"
    },
    {
      "kind": "pattern",
      "lang": "node",
      "file": "C:\\Users\\Ckhadar\\Downloads\\AI_Baseline_Map\\tmp\\analyzer\\741e5598-b64c-4f9c-9af0-4302e358d057-analyzer-fixture-3.js",
      "line": 32,
      "status": "affected",
      "reason": "code-quality",
      "issue": "console.log should be removed in production",
      "pattern": "console-log",
      "quickFix": "Use proper logging library or remove debug statements"
    },
    {
      "kind": "pattern",
      "lang": "node",
      "file": "C:\\Users\\Ckhadar\\Downloads\\AI_Baseline_Map\\tmp\\analyzer\\741e5598-b64c-4f9c-9af0-4302e358d057-analyzer-fixture-3.js",
      "line": 160,
      "status": "affected",
      "reason": "code-quality",
      "issue": "Trailing whitespace detected",
      "pattern": "trailing-whitespace",
      "quickFix": "Remove trailing whitespace"
    },
    {
      "kind": "pattern",
      "lang": "node",
      "file": "C:\\Users\\Ckhadar\\Downloads\\AI_Baseline_Map\\tmp\\analyzer\\741e5598-b64c-4f9c-9af0-4302e358d057-analyzer-fixture-3.js",
      "line": 201,
      "status": "affected",
      "reason": "code-quality",
      "issue": "console.log should be removed in production",
      "pattern": "console-log",
      "quickFix": "Use proper logging library or remove debug statements"
    }
  ],
  "summary": {
    "ok": 0,
    "affected": 98,
    "unknown": 0,
    "byLanguage": {
      "node": {
        "ok": 0,
        "affected": 98,
        "unknown": 0
      }
    }
  },
  "metadata": {
    "analysisId": "e2cc2b4d-d094-44f2-a3c1-7f2e84147057",
    "timestamp": "2025-10-01T05:27:40.119Z",
    "projectName": "C:\\Users\\Ckhadar\\Downloads\\AI_Baseline_Map\\tmp\\analyzer\\741e5598-b64c-4f9c-9af0-4302e358d057-analyzer-fixture-3.js",
    "detectedLanguages": [
      "node"
    ],
    "totalFiles": 1,
    "scannedFiles": 1,
    "skippedFiles": 0,
    "groqAnalysis": [
      {
        "analysis": "## Summary\nThis JavaScript file contains a mix of Node.js-specific features and web-compliant code. It uses top-level await, dynamic imports, and various Node.js APIs, which are not baseline web features. However, it also includes some web-compliant code, such as the use of `export` and `import` statements.\n\n## Score: 30 - FAIL\nThe file fails to comply with baseline web features due to its extensive use of Node.js-specific APIs and features.\n\n## Baseline Features Analysis\n| Feature | Status | Browser Support | Recommendation |\n|---------|--------|-----------------|----------------|\n| Top-level await | Limited | Not supported in most browsers | Avoid using top-level await in web code |\n| Dynamic imports | Limited | Not supported in most browsers | Use import() instead of dynamic imports |\n| Node.js fs/promises | Limited | Not supported in most browsers | Use the Fetch API or the File System API instead |\n| Node.js events | Limited | Not supported in most browsers | Use the EventTarget API instead |\n| Node.js child_process | Limited | Not supported in most browsers | Avoid using child_process.exec, use the Fetch API or the File System API instead |\n| Node.js util | Limited | Not supported in most browsers | Avoid using util.promisify, use the Fetch API or the File System API instead |\n| Export and import | Widely Available | Supported in most browsers | Use export and import statements as is |\n| Math.random() | Widely Available | Supported in most browsers | Avoid using Math.random() for generating secure randomness |\n\n## Issues Found\n| Severity | Issue | Affected Feature | Fix |\n|----------|-------|------------------|-----|\n| HIGH | EventEmitter listener leak | EventEmitter | Use a WeakEventEmitter or a custom event emitter that handles listener removal |\n| HIGH | Shell injection risk via child_process.exec | child_process.exec | Avoid using child_process.exec, use the Fetch API or the File System API instead |\n| HIGH | Sync FS in async context | fs/promises | Use the Fetch API or the File System API instead |\n| HIGH | Insecure randomness | Math.random() | Use a secure random number generator, such as crypto.getRandomValues() |\n| HIGH | Hardcoded secrets | HARDCODED_KEY | Avoid hardcoding secrets, use environment variables or a secrets manager instead |\n| HIGH | Misused Maps/Sets/WeakMap | Maps/Sets/WeakMap | Avoid mutating Maps/Sets/WeakMap during iteration |\n| HIGH | for..in over arrays | for..in | Avoid using for..in over arrays, use a for loop instead |\n| HIGH | Mixed timers | timers | Avoid mixing timers, use a consistent timing mechanism instead |\n| HIGH | Dangling promises | promises | Avoid using dangling promises, use a promise library or a custom promise implementation instead |\n| HIGH | Double-await | await | Avoid using double-await, use a single await statement instead |\n| HIGH | Redundant awaits | await | Avoid using redundant awaits, use a single await statement instead |\n| HIGH | Cross-origin postMessage '*' wildcard | postMessage | Avoid using the '*' wildcard, use a specific origin instead |\n| HIGH | SharedArrayBuffer/Atomics misuse | SharedArrayBuffer/Atomics | Avoid using SharedArrayBuffer/Atomics, use a different concurrency mechanism instead |\n| HIGH | Top-level side effects and environment dependence | top-level await | Avoid using top-level side effects and environment dependence, use a different execution context instead |\n\n## Code Improvements\n```js\n// Replace top-level await with a function that returns a promise\nasync function init() {\n  const fs = await import('node:fs/promises').then(m => m).catch(() => null);\n  const nodeFs = await import('node:fs').then(m => m).catch(() => null);\n  const path = await import('node:path').then(m => m).catch(() => null);\n  const { EventEmitter } = await import('node:events').then(m => m).catch(() => ({ EventEmitter: class {} }));\n  const { exec } = await import('node:child_process').then(m => m).catch(() => ({ exec: () => {} }));\n  const { promisify } = await import('node:util').then(m => m).catch(() => ({ promisify: (f) => f }));\n  const execP = promisify(exec);\n  return { fs, nodeFs, path, EventEmitter, exec, promisify, execP };\n}\n\n// Replace dynamic imports with static imports\nimport { VERSION } from './version.js';\nimport { HARDCODED_KEY } from './secrets.js';\n\n// Replace Node.js fs/promises with the Fetch API or the File System API\nasync function readFile(file) {\n  const response = await fetch(file);\n  const text = await response.text();\n  return text;\n}\n\n// Replace Node.js events with the EventTarget API\nclass CustomEventEmitter extends EventTarget {\n  constructor() {\n    super();\n  }\n  emit(event, ...args) {\n    this.dispatchEvent(new CustomEvent(event, args));\n  }\n}\n\n// Replace Node.js child_process with the Fetch API or the File System API\nasync function execCommand(command) {\n  const response = await fetch(command);\n  const text = await response.text();\n  return text;\n}\n\n// Replace Node.js util with the Fetch API or the File System API\nasync function promisifyFunction(func) {\n  return new Promise((resolve, reject) => {\n    func((err, result) => {\n      if (err) reject(err);\n      else resolve(result);\n    });\n  });\n}\n\n// Replace Math.random() with a secure random number generator\nasync function generateSecureRandomNumber() {\n  const array = new Uint32Array(1);\n  crypto.getRandomValues(array);\n  return array[0];\n}\n\n// Replace hardcoded secrets with environment variables or a secrets",
        "filename": "C:\\Users\\Ckhadar\\Downloads\\AI_Baseline_Map\\tmp\\analyzer\\741e5598-b64c-4f9c-9af0-4302e358d057-analyzer-fixture-3.js",
        "timestamp": "2025-10-01T05:27:40.089Z"
      }
    ]
  }
}