{
  "findings": [
    {
      "kind": "dependency",
      "lang": "node",
      "component": "autoprefixer",
      "foundVersion": "^10.4.17",
      "baselineRequired": null,
      "status": "unknown",
      "reason": "no-baseline-rule",
      "file": "C:\\Users\\Ckhadar\\Downloads\\AI_Baseline_Map\\tmp\\analyzer\\94212982-e504-47c2-a7e3-979fed28582f-package.json"
    },
    {
      "kind": "dependency",
      "lang": "node",
      "component": "busboy",
      "foundVersion": "^1.6.0",
      "baselineRequired": null,
      "status": "unknown",
      "reason": "no-baseline-rule",
      "file": "C:\\Users\\Ckhadar\\Downloads\\AI_Baseline_Map\\tmp\\analyzer\\94212982-e504-47c2-a7e3-979fed28582f-package.json"
    },
    {
      "kind": "dependency",
      "lang": "node",
      "component": "class-variance-authority",
      "foundVersion": "^0.7.0",
      "baselineRequired": null,
      "status": "unknown",
      "reason": "no-baseline-rule",
      "file": "C:\\Users\\Ckhadar\\Downloads\\AI_Baseline_Map\\tmp\\analyzer\\94212982-e504-47c2-a7e3-979fed28582f-package.json"
    },
    {
      "kind": "dependency",
      "lang": "node",
      "component": "clsx",
      "foundVersion": "^2.1.0",
      "baselineRequired": null,
      "status": "unknown",
      "reason": "no-baseline-rule",
      "file": "C:\\Users\\Ckhadar\\Downloads\\AI_Baseline_Map\\tmp\\analyzer\\94212982-e504-47c2-a7e3-979fed28582f-package.json"
    },
    {
      "kind": "dependency",
      "lang": "node",
      "component": "cors",
      "foundVersion": "^2.8.5",
      "baselineRequired": null,
      "status": "unknown",
      "reason": "no-baseline-rule",
      "file": "C:\\Users\\Ckhadar\\Downloads\\AI_Baseline_Map\\tmp\\analyzer\\94212982-e504-47c2-a7e3-979fed28582f-package.json"
    },
    {
      "kind": "dependency",
      "lang": "node",
      "component": "d3",
      "foundVersion": "^7.9.0",
      "baselineRequired": null,
      "status": "unknown",
      "reason": "no-baseline-rule",
      "file": "C:\\Users\\Ckhadar\\Downloads\\AI_Baseline_Map\\tmp\\analyzer\\94212982-e504-47c2-a7e3-979fed28582f-package.json"
    },
    {
      "kind": "dependency",
      "lang": "node",
      "component": "express",
      "foundVersion": "^4.19.2",
      "baselineRequired": ">=4.18.0",
      "status": "ok",
      "reason": "meets-baseline",
      "file": "C:\\Users\\Ckhadar\\Downloads\\AI_Baseline_Map\\tmp\\analyzer\\94212982-e504-47c2-a7e3-979fed28582f-package.json",
      "quickFix": "npm install express@>=4.18.0"
    },
    {
      "kind": "dependency",
      "lang": "node",
      "component": "formidable",
      "foundVersion": "^3.5.1",
      "baselineRequired": null,
      "status": "unknown",
      "reason": "no-baseline-rule",
      "file": "C:\\Users\\Ckhadar\\Downloads\\AI_Baseline_Map\\tmp\\analyzer\\94212982-e504-47c2-a7e3-979fed28582f-package.json"
    },
    {
      "kind": "dependency",
      "lang": "node",
      "component": "groq-sdk",
      "foundVersion": "^0.33.0",
      "baselineRequired": null,
      "status": "unknown",
      "reason": "no-baseline-rule",
      "file": "C:\\Users\\Ckhadar\\Downloads\\AI_Baseline_Map\\tmp\\analyzer\\94212982-e504-47c2-a7e3-979fed28582f-package.json"
    },
    {
      "kind": "dependency",
      "lang": "node",
      "component": "lucide-react",
      "foundVersion": "^0.400.0",
      "baselineRequired": null,
      "status": "unknown",
      "reason": "no-baseline-rule",
      "file": "C:\\Users\\Ckhadar\\Downloads\\AI_Baseline_Map\\tmp\\analyzer\\94212982-e504-47c2-a7e3-979fed28582f-package.json"
    },
    {
      "kind": "dependency",
      "lang": "node",
      "component": "multer",
      "foundVersion": "^1.4.5-lts.1",
      "baselineRequired": null,
      "status": "unknown",
      "reason": "no-baseline-rule",
      "file": "C:\\Users\\Ckhadar\\Downloads\\AI_Baseline_Map\\tmp\\analyzer\\94212982-e504-47c2-a7e3-979fed28582f-package.json"
    },
    {
      "kind": "dependency",
      "lang": "node",
      "component": "next",
      "foundVersion": "^15.0.0",
      "baselineRequired": ">=13.0.0",
      "status": "ok",
      "reason": "meets-baseline",
      "file": "C:\\Users\\Ckhadar\\Downloads\\AI_Baseline_Map\\tmp\\analyzer\\94212982-e504-47c2-a7e3-979fed28582f-package.json",
      "quickFix": "npm install next@>=13.0.0"
    },
    {
      "kind": "dependency",
      "lang": "node",
      "component": "papaparse",
      "foundVersion": "^5.4.1",
      "baselineRequired": null,
      "status": "unknown",
      "reason": "no-baseline-rule",
      "file": "C:\\Users\\Ckhadar\\Downloads\\AI_Baseline_Map\\tmp\\analyzer\\94212982-e504-47c2-a7e3-979fed28582f-package.json"
    },
    {
      "kind": "dependency",
      "lang": "node",
      "component": "postcss",
      "foundVersion": "^8.4.35",
      "baselineRequired": null,
      "status": "unknown",
      "reason": "no-baseline-rule",
      "file": "C:\\Users\\Ckhadar\\Downloads\\AI_Baseline_Map\\tmp\\analyzer\\94212982-e504-47c2-a7e3-979fed28582f-package.json"
    },
    {
      "kind": "dependency",
      "lang": "node",
      "component": "react",
      "foundVersion": "^19.1.1",
      "baselineRequired": ">=18.0.0",
      "status": "ok",
      "reason": "meets-baseline",
      "file": "C:\\Users\\Ckhadar\\Downloads\\AI_Baseline_Map\\tmp\\analyzer\\94212982-e504-47c2-a7e3-979fed28582f-package.json",
      "quickFix": "npm install react@>=18.0.0"
    },
    {
      "kind": "dependency",
      "lang": "node",
      "component": "react-dom",
      "foundVersion": "^19.1.1",
      "baselineRequired": null,
      "status": "unknown",
      "reason": "no-baseline-rule",
      "file": "C:\\Users\\Ckhadar\\Downloads\\AI_Baseline_Map\\tmp\\analyzer\\94212982-e504-47c2-a7e3-979fed28582f-package.json"
    },
    {
      "kind": "dependency",
      "lang": "node",
      "component": "react-dropzone",
      "foundVersion": "^14.2.3",
      "baselineRequired": null,
      "status": "unknown",
      "reason": "no-baseline-rule",
      "file": "C:\\Users\\Ckhadar\\Downloads\\AI_Baseline_Map\\tmp\\analyzer\\94212982-e504-47c2-a7e3-979fed28582f-package.json"
    },
    {
      "kind": "dependency",
      "lang": "node",
      "component": "semver",
      "foundVersion": "^7.6.3",
      "baselineRequired": null,
      "status": "unknown",
      "reason": "no-baseline-rule",
      "file": "C:\\Users\\Ckhadar\\Downloads\\AI_Baseline_Map\\tmp\\analyzer\\94212982-e504-47c2-a7e3-979fed28582f-package.json"
    },
    {
      "kind": "dependency",
      "lang": "node",
      "component": "tailwind-merge",
      "foundVersion": "^2.2.1",
      "baselineRequired": null,
      "status": "unknown",
      "reason": "no-baseline-rule",
      "file": "C:\\Users\\Ckhadar\\Downloads\\AI_Baseline_Map\\tmp\\analyzer\\94212982-e504-47c2-a7e3-979fed28582f-package.json"
    },
    {
      "kind": "dependency",
      "lang": "node",
      "component": "tailwindcss",
      "foundVersion": "^3.4.0",
      "baselineRequired": null,
      "status": "unknown",
      "reason": "no-baseline-rule",
      "file": "C:\\Users\\Ckhadar\\Downloads\\AI_Baseline_Map\\tmp\\analyzer\\94212982-e504-47c2-a7e3-979fed28582f-package.json"
    },
    {
      "kind": "dependency",
      "lang": "node",
      "component": "unzipper",
      "foundVersion": "^0.10.14",
      "baselineRequired": null,
      "status": "unknown",
      "reason": "no-baseline-rule",
      "file": "C:\\Users\\Ckhadar\\Downloads\\AI_Baseline_Map\\tmp\\analyzer\\94212982-e504-47c2-a7e3-979fed28582f-package.json"
    },
    {
      "kind": "dependency",
      "lang": "node",
      "component": "web-features",
      "foundVersion": "^3.1.0",
      "baselineRequired": null,
      "status": "unknown",
      "reason": "no-baseline-rule",
      "file": "C:\\Users\\Ckhadar\\Downloads\\AI_Baseline_Map\\tmp\\analyzer\\94212982-e504-47c2-a7e3-979fed28582f-package.json"
    },
    {
      "kind": "dependency",
      "lang": "node",
      "component": "yaml",
      "foundVersion": "^2.6.0",
      "baselineRequired": null,
      "status": "unknown",
      "reason": "no-baseline-rule",
      "file": "C:\\Users\\Ckhadar\\Downloads\\AI_Baseline_Map\\tmp\\analyzer\\94212982-e504-47c2-a7e3-979fed28582f-package.json"
    },
    {
      "kind": "dependency",
      "lang": "node",
      "component": "zod",
      "foundVersion": "^3.23.8",
      "baselineRequired": null,
      "status": "unknown",
      "reason": "no-baseline-rule",
      "file": "C:\\Users\\Ckhadar\\Downloads\\AI_Baseline_Map\\tmp\\analyzer\\94212982-e504-47c2-a7e3-979fed28582f-package.json"
    }
  ],
  "summary": {
    "ok": 3,
    "affected": 0,
    "unknown": 21,
    "byLanguage": {}
  },
  "metadata": {
    "analysisId": "5b0626c5-660d-4c2f-a490-53044b8227cb",
    "timestamp": "2025-09-28T17:27:54.546Z",
    "projectName": "C:\\Users\\Ckhadar\\Downloads\\AI_Baseline_Map\\tmp\\analyzer\\94212982-e504-47c2-a7e3-979fed28582f-package.json",
    "detectedLanguages": [],
    "totalFiles": 1,
    "scannedFiles": 1,
    "skippedFiles": 0,
    "groqAnalysis": []
  }
}